<?xml version="1.0" encoding="UTF-8"?>
<objects serializationModel="Studio.02.01.00">
	<object class="AudioFile" id="{2f09eadc-9130-4a20-b6c6-255d94f48d0f}">
		<property name="assetPath">
			<value>DUBLAGEM FINAL/parte 2/thiago parte 2/15 - Como assim, doutor.mp3</value>
		</property>
		<property name="frequencyInKHz">
			<value>44.0999985</value>
		</property>
		<property name="channelCount">
			<value>2</value>
		</property>
		<property name="length">
			<value>1.933061224489796</value>
		</property>
		<relationship name="masterAssetFolder">
			<destination>{cc18a13e-ea8a-488c-8daf-6730caa6d071}</destination>
		</relationship>
	</object>
</objects>
