<?xml version="1.0" encoding="UTF-8"?>
<objects serializationModel="Studio.02.01.00">
	<object class="AudioFile" id="{775764ce-b72a-4f42-905e-d2b248d4dc21}">
		<property name="assetPath">
			<value>DUBLAGEM FINAL/parte 2/thiago parte 2/46 - Que olhos são esses.mp3</value>
		</property>
		<property name="frequencyInKHz">
			<value>44.0999985</value>
		</property>
		<property name="channelCount">
			<value>2</value>
		</property>
		<property name="length">
			<value>8.4375510204081632</value>
		</property>
		<relationship name="masterAssetFolder">
			<destination>{cc18a13e-ea8a-488c-8daf-6730caa6d071}</destination>
		</relationship>
	</object>
</objects>
